{
	"start":	{
		"connected":	[{
				"socket":	5,
				"local_host":	"10.233.64.6",
				"local_port":	45287,
				"remote_host":	"10.233.66.4",
				"remote_port":	5201
			}],
		"version":	"iperf 3.12",
		"system_info":	"Linux iperf-client 6.8.0-94-generic #96-Ubuntu SMP PREEMPT_DYNAMIC Fri Jan  9 20:36:55 UTC 2026 x86_64",
		"timestamp":	{
			"time":	"Tue, 26 May 2026 02:28:11 GMT",
			"timesecs":	1779762491
		},
		"connecting_to":	{
			"host":	"10.233.66.4",
			"port":	5201
		},
		"cookie":	"wozdl57zlwuddrrublc2lxodetvh7w725ogu",
		"target_bitrate":	0,
		"sock_bufsize":	0,
		"sndbuf_actual":	212992,
		"rcvbuf_actual":	212992,
		"test_start":	{
			"protocol":	"UDP",
			"num_streams":	1,
			"blksize":	64,
			"omit":	0,
			"duration":	60,
			"bytes":	0,
			"blocks":	0,
			"reverse":	0,
			"tos":	0,
			"target_bitrate":	0
		}
	},
	"intervals":	[{
			"streams":	[{
					"socket":	5,
					"start":	0,
					"end":	1.000015,
					"seconds":	1.0000150203704834,
					"bytes":	21673600,
					"bits_per_second":	173386195.67510426,
					"packets":	338650,
					"omitted":	false,
					"sender":	true
				}],
			"sum":	{
				"start":	0,
				"end":	1.000015,
				"seconds":	1.0000150203704834,
				"bytes":	21673600,
				"bits_per_second":	173386195.67510426,
				"packets":	338650,
				"omitted":	false,
				"sender":	true
			}
		}, {
			"streams":	[{
					"socket":	5,
					"start":	1.000015,
					"end":	2.000042,
					"seconds":	1.0000269412994385,
					"bytes":	24962560,
					"bits_per_second":	199695099.95451573,
					"packets":	390040,
					"omitted":	false,
					"sender":	true
				}],
			"sum":	{
				"start":	1.000015,
				"end":	2.000042,
				"seconds":	1.0000269412994385,
				"bytes":	24962560,
				"bits_per_second":	199695099.95451573,
				"packets":	390040,
				"omitted":	false,
				"sender":	true
			}
		}, {
			"streams":	[{
					"socket":	5,
					"start":	2.000042,
					"end":	3.000014,
					"seconds":	0.99997198581695557,
					"bytes":	27875200,
					"bits_per_second":	223007847.38265693,
					"packets":	435550,
					"omitted":	false,
					"sender":	true
				}],
			"sum":	{
				"start":	2.000042,
				"end":	3.000014,
				"seconds":	0.99997198581695557,
				"bytes":	27875200,
				"bits_per_second":	223007847.38265693,
				"packets":	435550,
				"omitted":	false,
				"sender":	true
			}
		}, {
			"streams":	[{
					"socket":	5,
					"start":	3.000014,
					"end":	4.000017,
					"seconds":	1.0000029802322388,
					"bytes":	27534720,
					"bits_per_second":	220277103.52307463,
					"packets":	430230,
					"omitted":	false,
					"sender":	true
				}],
			"sum":	{
				"start":	3.000014,
				"end":	4.000017,
				"seconds":	1.0000029802322388,
				"bytes":	27534720,
				"bits_per_second":	220277103.52307463,
				"packets":	430230,
				"omitted":	false,
				"sender":	true
			}
		}, {
			"streams":	[{
					"socket":	5,
					"start":	4.000017,
					"end":	5.00002,
					"seconds":	1.0000029802322388,
					"bytes":	27596160,
					"bits_per_second":	220768622.05823523,
					"packets":	431190,
					"omitted":	false,
					"sender":	true
				}],
			"sum":	{
				"start":	4.000017,
				"end":	5.00002,
				"seconds":	1.0000029802322388,
				"bytes":	27596160,
				"bits_per_second":	220768622.05823523,
				"packets":	431190,
				"omitted":	false,
				"sender":	true
			}
		}, {
			"streams":	[{
					"socket":	5,
					"start":	5.00002,
					"end":	6.000007,
					"seconds":	0.999987006187439,
					"bytes":	28382080,
					"bits_per_second":	227059590.36975744,
					"packets":	443470,
					"omitted":	false,
					"sender":	true
				}],
			"sum":	{
				"start":	5.00002,
				"end":	6.000007,
				"seconds":	0.999987006187439,
				"bytes":	28382080,
				"bits_per_second":	227059590.36975744,
				"packets":	443470,
				"omitted":	false,
				"sender":	true
			}
		}, {
			"streams":	[{
					"socket":	5,
					"start":	6.000007,
					"end":	7.000016,
					"seconds":	1.0000089406967163,
					"bytes":	24108160,
					"bits_per_second":	192863555.66544116,
					"packets":	376690,
					"omitted":	false,
					"sender":	true
				}],
			"sum":	{
				"start":	6.000007,
				"end":	7.000016,
				"seconds":	1.0000089406967163,
				"bytes":	24108160,
				"bits_per_second":	192863555.66544116,
				"packets":	376690,
				"omitted":	false,
				"sender":	true
			}
		}, {
			"streams":	[{
					"socket":	5,
					"start":	7.000016,
					"end":	8.000014,
					"seconds":	0.99999797344207764,
					"bytes":	25792640,
					"bits_per_second":	206341538.16307887,
					"packets":	403010,
					"omitted":	false,
					"sender":	true
				}],
			"sum":	{
				"start":	7.000016,
				"end":	8.000014,
				"seconds":	0.99999797344207764,
				"bytes":	25792640,
				"bits_per_second":	206341538.16307887,
				"packets":	403010,
				"omitted":	false,
				"sender":	true
			}
		}, {
			"streams":	[{
					"socket":	5,
					"start":	8.000014,
					"end":	9.00001,
					"seconds":	0.9999960064888,
					"bytes":	28169600,
					"bits_per_second":	225357699.96849883,
					"packets":	440150,
					"omitted":	false,
					"sender":	true
				}],
			"sum":	{
				"start":	8.000014,
				"end":	9.00001,
				"seconds":	0.9999960064888,
				"bytes":	28169600,
				"bits_per_second":	225357699.96849883,
				"packets":	440150,
				"omitted":	false,
				"sender":	true
			}
		}, {
			"streams":	[{
					"socket":	5,
					"start":	9.00001,
					"end":	10.000005,
					"seconds":	0.999994993209839,
					"bytes":	28432000,
					"bits_per_second":	227457138.83016476,
					"packets":	444250,
					"omitted":	false,
					"sender":	true
				}],
			"sum":	{
				"start":	9.00001,
				"end":	10.000005,
				"seconds":	0.999994993209839,
				"bytes":	28432000,
				"bits_per_second":	227457138.83016476,
				"packets":	444250,
				"omitted":	false,
				"sender":	true
			}
		}, {
			"streams":	[{
					"socket":	5,
					"start":	10.000005,
					"end":	11.000007,
					"seconds":	1.0000020265579224,
					"bytes":	27962880,
					"bits_per_second":	223702586.65375078,
					"packets":	436920,
					"omitted":	false,
					"sender":	true
				}],
			"sum":	{
				"start":	10.000005,
				"end":	11.000007,
				"seconds":	1.0000020265579224,
				"bytes":	27962880,
				"bits_per_second":	223702586.65375078,
				"packets":	436920,
				"omitted":	false,
				"sender":	true
			}
		}, {
			"streams":	[{
					"socket":	5,
					"start":	11.000007,
					"end":	12.000014,
					"seconds":	1.0000070333480835,
					"bytes":	27584000,
					"bits_per_second":	220670447.94792783,
					"packets":	431000,
					"omitted":	false,
					"sender":	true
				}],
			"sum":	{
				"start":	11.000007,
				"end":	12.000014,
				"seconds":	1.0000070333480835,
				"bytes":	27584000,
				"bits_per_second":	220670447.94792783,
				"packets":	431000,
				"omitted":	false,
				"sender":	true
			}
		}, {
			"streams":	[{
					"socket":	5,
					"start":	12.000014,
					"end":	13.000012,
					"seconds":	0.99999797344207764,
					"bytes":	27802880,
					"bits_per_second":	222423490.7540873,
					"packets":	434420,
					"omitted":	false,
					"sender":	true
				}],
			"sum":	{
				"start":	12.000014,
				"end":	13.000012,
				"seconds":	0.99999797344207764,
				"bytes":	27802880,
				"bits_per_second":	222423490.7540873,
				"packets":	434420,
				"omitted":	false,
				"sender":	true
			}
		}, {
			"streams":	[{
					"socket":	5,
					"start":	13.000012,
					"end":	14.000007,
					"seconds":	0.999994993209839,
					"bytes":	28280960,
					"bits_per_second":	226248812.78032979,
					"packets":	441890,
					"omitted":	false,
					"sender":	true
				}],
			"sum":	{
				"start":	13.000012,
				"end":	14.000007,
				"seconds":	0.999994993209839,
				"bytes":	28280960,
				"bits_per_second":	226248812.78032979,
				"packets":	441890,
				"omitted":	false,
				"sender":	true
			}
		}, {
			"streams":	[{
					"socket":	5,
					"start":	14.000007,
					"end":	15.000011,
					"seconds":	1.0000040531158447,
					"bytes":	28073600,
					"bits_per_second":	224587889.71926564,
					"packets":	438650,
					"omitted":	false,
					"sender":	true
				}],
			"sum":	{
				"start":	14.000007,
				"end":	15.000011,
				"seconds":	1.0000040531158447,
				"bytes":	28073600,
				"bits_per_second":	224587889.71926564,
				"packets":	438650,
				"omitted":	false,
				"sender":	true
			}
		}, {
			"streams":	[{
					"socket":	5,
					"start":	15.000011,
					"end":	16.000011,
					"seconds":	1,
					"bytes":	28470400,
					"bits_per_second":	227763200,
					"packets":	444850,
					"omitted":	false,
					"sender":	true
				}],
			"sum":	{
				"start":	15.000011,
				"end":	16.000011,
				"seconds":	1,
				"bytes":	28470400,
				"bits_per_second":	227763200,
				"packets":	444850,
				"omitted":	false,
				"sender":	true
			}
		}, {
			"streams":	[{
					"socket":	5,
					"start":	16.000011,
					"end":	17.00002,
					"seconds":	1.0000089406967163,
					"bytes":	28627840,
					"bits_per_second":	229020672.39562634,
					"packets":	447310,
					"omitted":	false,
					"sender":	true
				}],
			"sum":	{
				"start":	16.000011,
				"end":	17.00002,
				"seconds":	1.0000089406967163,
				"bytes":	28627840,
				"bits_per_second":	229020672.39562634,
				"packets":	447310,
				"omitted":	false,
				"sender":	true
			}
		}, {
			"streams":	[{
					"socket":	5,
					"start":	17.00002,
					"end":	18.000014,
					"seconds":	0.99999397993087769,
					"bytes":	28406400,
					"bits_per_second":	227252568.076168,
					"packets":	443850,
					"omitted":	false,
					"sender":	true
				}],
			"sum":	{
				"start":	17.00002,
				"end":	18.000014,
				"seconds":	0.99999397993087769,
				"bytes":	28406400,
				"bits_per_second":	227252568.076168,
				"packets":	443850,
				"omitted":	false,
				"sender":	true
			}
		}, {
			"streams":	[{
					"socket":	5,
					"start":	18.000014,
					"end":	19.000019,
					"seconds":	1.0000050067901611,
					"bytes":	28659840,
					"bits_per_second":	229277572.05530807,
					"packets":	447810,
					"omitted":	false,
					"sender":	true
				}],
			"sum":	{
				"start":	18.000014,
				"end":	19.000019,
				"seconds":	1.0000050067901611,
				"bytes":	28659840,
				"bits_per_second":	229277572.05530807,
				"packets":	447810,
				"omitted":	false,
				"sender":	true
			}
		}, {
			"streams":	[{
					"socket":	5,
					"start":	19.000019,
					"end":	20.000006,
					"seconds":	0.999987006187439,
					"bytes":	28513920,
					"bits_per_second":	228114324.07476953,
					"packets":	445530,
					"omitted":	false,
					"sender":	true
				}],
			"sum":	{
				"start":	19.000019,
				"end":	20.000006,
				"seconds":	0.999987006187439,
				"bytes":	28513920,
				"bits_per_second":	228114324.07476953,
				"packets":	445530,
				"omitted":	false,
				"sender":	true
			}
		}, {
			"streams":	[{
					"socket":	5,
					"start":	20.000006,
					"end":	21.000018,
					"seconds":	1.0000120401382446,
					"bytes":	28306560,
					"bits_per_second":	226449753.51366222,
					"packets":	442290,
					"omitted":	false,
					"sender":	true
				}],
			"sum":	{
				"start":	20.000006,
				"end":	21.000018,
				"seconds":	1.0000120401382446,
				"bytes":	28306560,
				"bits_per_second":	226449753.51366222,
				"packets":	442290,
				"omitted":	false,
				"sender":	true
			}
		}, {
			"streams":	[{
					"socket":	5,
					"start":	21.000018,
					"end":	22.000017,
					"seconds":	0.99999898672103882,
					"bytes":	25024000,
					"bits_per_second":	200192202.85054734,
					"packets":	391000,
					"omitted":	false,
					"sender":	true
				}],
			"sum":	{
				"start":	21.000018,
				"end":	22.000017,
				"seconds":	0.99999898672103882,
				"bytes":	25024000,
				"bits_per_second":	200192202.85054734,
				"packets":	391000,
				"omitted":	false,
				"sender":	true
			}
		}, {
			"streams":	[{
					"socket":	5,
					"start":	22.000017,
					"end":	23.00002,
					"seconds":	1.0000029802322388,
					"bytes":	23194240,
					"bits_per_second":	185553367.00787362,
					"packets":	362410,
					"omitted":	false,
					"sender":	true
				}],
			"sum":	{
				"start":	22.000017,
				"end":	23.00002,
				"seconds":	1.0000029802322388,
				"bytes":	23194240,
				"bits_per_second":	185553367.00787362,
				"packets":	362410,
				"omitted":	false,
				"sender":	true
			}
		}, {
			"streams":	[{
					"socket":	5,
					"start":	23.00002,
					"end":	24.00002,
					"seconds":	1,
					"bytes":	28064640,
					"bits_per_second":	224517120,
					"packets":	438510,
					"omitted":	false,
					"sender":	true
				}],
			"sum":	{
				"start":	23.00002,
				"end":	24.00002,
				"seconds":	1,
				"bytes":	28064640,
				"bits_per_second":	224517120,
				"packets":	438510,
				"omitted":	false,
				"sender":	true
			}
		}, {
			"streams":	[{
					"socket":	5,
					"start":	24.00002,
					"end":	25.000013,
					"seconds":	0.99999302625656128,
					"bytes":	28591360,
					"bits_per_second":	228732475.12159759,
					"packets":	446740,
					"omitted":	false,
					"sender":	true
				}],
			"sum":	{
				"start":	24.00002,
				"end":	25.000013,
				"seconds":	0.99999302625656128,
				"bytes":	28591360,
				"bits_per_second":	228732475.12159759,
				"packets":	446740,
				"omitted":	false,
				"sender":	true
			}
		}, {
			"streams":	[{
					"socket":	5,
					"start":	25.000013,
					"end":	26.000023,
					"seconds":	1.0000100135803223,
					"bytes":	28544000,
					"bits_per_second":	228349713.40180328,
					"packets":	446000,
					"omitted":	false,
					"sender":	true
				}],
			"sum":	{
				"start":	25.000013,
				"end":	26.000023,
				"seconds":	1.0000100135803223,
				"bytes":	28544000,
				"bits_per_second":	228349713.40180328,
				"packets":	446000,
				"omitted":	false,
				"sender":	true
			}
		}, {
			"streams":	[{
					"socket":	5,
					"start":	26.000023,
					"end":	27.000008,
					"seconds":	0.9999849796295166,
					"bytes":	28332160,
					"bits_per_second":	226660684.52745563,
					"packets":	442690,
					"omitted":	false,
					"sender":	true
				}],
			"sum":	{
				"start":	26.000023,
				"end":	27.000008,
				"seconds":	0.9999849796295166,
				"bytes":	28332160,
				"bits_per_second":	226660684.52745563,
				"packets":	442690,
				"omitted":	false,
				"sender":	true
			}
		}, {
			"streams":	[{
					"socket":	5,
					"start":	27.000008,
					"end":	28.000021,
					"seconds":	1.000012993812561,
					"bytes":	27688960,
					"bits_per_second":	221508801.75614935,
					"packets":	432640,
					"omitted":	false,
					"sender":	true
				}],
			"sum":	{
				"start":	27.000008,
				"end":	28.000021,
				"seconds":	1.000012993812561,
				"bytes":	27688960,
				"bits_per_second":	221508801.75614935,
				"packets":	432640,
				"omitted":	false,
				"sender":	true
			}
		}, {
			"streams":	[{
					"socket":	5,
					"start":	28.000021,
					"end":	29.000018,
					"seconds":	0.99999701976776123,
					"bytes":	28011520,
					"bits_per_second":	224092827.84867,
					"packets":	437680,
					"omitted":	false,
					"sender":	true
				}],
			"sum":	{
				"start":	28.000021,
				"end":	29.000018,
				"seconds":	0.99999701976776123,
				"bytes":	28011520,
				"bits_per_second":	224092827.84867,
				"packets":	437680,
				"omitted":	false,
				"sender":	true
			}
		}, {
			"streams":	[{
					"socket":	5,
					"start":	29.000018,
					"end":	30.00001,
					"seconds":	0.9999920129776,
					"bytes":	28578560,
					"bits_per_second":	228630306.07537591,
					"packets":	446540,
					"omitted":	false,
					"sender":	true
				}],
			"sum":	{
				"start":	29.000018,
				"end":	30.00001,
				"seconds":	0.9999920129776,
				"bytes":	28578560,
				"bits_per_second":	228630306.07537591,
				"packets":	446540,
				"omitted":	false,
				"sender":	true
			}
		}, {
			"streams":	[{
					"socket":	5,
					"start":	30.00001,
					"end":	31.000004,
					"seconds":	0.99999397993087769,
					"bytes":	28264960,
					"bits_per_second":	226121041.26429841,
					"packets":	441640,
					"omitted":	false,
					"sender":	true
				}],
			"sum":	{
				"start":	30.00001,
				"end":	31.000004,
				"seconds":	0.99999397993087769,
				"bytes":	28264960,
				"bits_per_second":	226121041.26429841,
				"packets":	441640,
				"omitted":	false,
				"sender":	true
			}
		}, {
			"streams":	[{
					"socket":	5,
					"start":	31.000004,
					"end":	32.000028,
					"seconds":	1.0000239610672,
					"bytes":	28432640,
					"bits_per_second":	227455669.91940811,
					"packets":	444260,
					"omitted":	false,
					"sender":	true
				}],
			"sum":	{
				"start":	31.000004,
				"end":	32.000028,
				"seconds":	1.0000239610672,
				"bytes":	28432640,
				"bits_per_second":	227455669.91940811,
				"packets":	444260,
				"omitted":	false,
				"sender":	true
			}
		}, {
			"streams":	[{
					"socket":	5,
					"start":	32.000028,
					"end":	33.000024,
					"seconds":	0.9999960064888,
					"bytes":	29235840,
					"bits_per_second":	233887654.0329659,
					"packets":	456810,
					"omitted":	false,
					"sender":	true
				}],
			"sum":	{
				"start":	32.000028,
				"end":	33.000024,
				"seconds":	0.9999960064888,
				"bytes":	29235840,
				"bits_per_second":	233887654.0329659,
				"packets":	456810,
				"omitted":	false,
				"sender":	true
			}
		}, {
			"streams":	[{
					"socket":	5,
					"start":	33.000024,
					"end":	34.000015,
					"seconds":	0.999990999698639,
					"bytes":	28562560,
					"bits_per_second":	228502536.59169111,
					"packets":	446290,
					"omitted":	false,
					"sender":	true
				}],
			"sum":	{
				"start":	33.000024,
				"end":	34.000015,
				"seconds":	0.999990999698639,
				"bytes":	28562560,
				"bits_per_second":	228502536.59169111,
				"packets":	446290,
				"omitted":	false,
				"sender":	true
			}
		}, {
			"streams":	[{
					"socket":	5,
					"start":	34.000015,
					"end":	35.000007,
					"seconds":	0.9999920129776,
					"bytes":	28872320,
					"bits_per_second":	230980404.84566745,
					"packets":	451130,
					"omitted":	false,
					"sender":	true
				}],
			"sum":	{
				"start":	34.000015,
				"end":	35.000007,
				"seconds":	0.9999920129776,
				"bytes":	28872320,
				"bits_per_second":	230980404.84566745,
				"packets":	451130,
				"omitted":	false,
				"sender":	true
			}
		}, {
			"streams":	[{
					"socket":	5,
					"start":	35.000007,
					"end":	36.000016,
					"seconds":	1.0000089406967163,
					"bytes":	29035520,
					"bits_per_second":	232282083.23634115,
					"packets":	453680,
					"omitted":	false,
					"sender":	true
				}],
			"sum":	{
				"start":	35.000007,
				"end":	36.000016,
				"seconds":	1.0000089406967163,
				"bytes":	29035520,
				"bits_per_second":	232282083.23634115,
				"packets":	453680,
				"omitted":	false,
				"sender":	true
			}
		}, {
			"streams":	[{
					"socket":	5,
					"start":	36.000016,
					"end":	37.000008,
					"seconds":	0.9999920129776,
					"bytes":	28233600,
					"bits_per_second":	225870604.0335739,
					"packets":	441150,
					"omitted":	false,
					"sender":	true
				}],
			"sum":	{
				"start":	36.000016,
				"end":	37.000008,
				"seconds":	0.9999920129776,
				"bytes":	28233600,
				"bits_per_second":	225870604.0335739,
				"packets":	441150,
				"omitted":	false,
				"sender":	true
			}
		}, {
			"streams":	[{
					"socket":	5,
					"start":	37.000008,
					"end":	38.000031,
					"seconds":	1.0000230073928833,
					"bytes":	28682880,
					"bits_per_second":	229457760.77514774,
					"packets":	448170,
					"omitted":	false,
					"sender":	true
				}],
			"sum":	{
				"start":	37.000008,
				"end":	38.000031,
				"seconds":	1.0000230073928833,
				"bytes":	28682880,
				"bits_per_second":	229457760.77514774,
				"packets":	448170,
				"omitted":	false,
				"sender":	true
			}
		}, {
			"streams":	[{
					"socket":	5,
					"start":	38.000031,
					"end":	39.000027,
					"seconds":	0.9999960064888,
					"bytes":	28853120,
					"bits_per_second":	230825881.80574423,
					"packets":	450830,
					"omitted":	false,
					"sender":	true
				}],
			"sum":	{
				"start":	38.000031,
				"end":	39.000027,
				"seconds":	0.9999960064888,
				"bytes":	28853120,
				"bits_per_second":	230825881.80574423,
				"packets":	450830,
				"omitted":	false,
				"sender":	true
			}
		}, {
			"streams":	[{
					"socket":	5,
					"start":	39.000027,
					"end":	40.000018,
					"seconds":	0.999990999698639,
					"bytes":	28947840,
					"bits_per_second":	231584804.33302966,
					"packets":	452310,
					"omitted":	false,
					"sender":	true
				}],
			"sum":	{
				"start":	39.000027,
				"end":	40.000018,
				"seconds":	0.999990999698639,
				"bytes":	28947840,
				"bits_per_second":	231584804.33302966,
				"packets":	452310,
				"omitted":	false,
				"sender":	true
			}
		}, {
			"streams":	[{
					"socket":	5,
					"start":	40.000018,
					"end":	41.000022,
					"seconds":	1.0000040531158447,
					"bytes":	29559680,
					"bits_per_second":	236476481.53342578,
					"packets":	461870,
					"omitted":	false,
					"sender":	true
				}],
			"sum":	{
				"start":	40.000018,
				"end":	41.000022,
				"seconds":	1.0000040531158447,
				"bytes":	29559680,
				"bits_per_second":	236476481.53342578,
				"packets":	461870,
				"omitted":	false,
				"sender":	true
			}
		}, {
			"streams":	[{
					"socket":	5,
					"start":	41.000022,
					"end":	42.000019,
					"seconds":	0.99999701976776123,
					"bytes":	29187840,
					"bits_per_second":	233503415.8944079,
					"packets":	456060,
					"omitted":	false,
					"sender":	true
				}],
			"sum":	{
				"start":	41.000022,
				"end":	42.000019,
				"seconds":	0.99999701976776123,
				"bytes":	29187840,
				"bits_per_second":	233503415.8944079,
				"packets":	456060,
				"omitted":	false,
				"sender":	true
			}
		}, {
			"streams":	[{
					"socket":	5,
					"start":	42.000019,
					"end":	43.000007,
					"seconds":	0.9999880194664,
					"bytes":	29484800,
					"bits_per_second":	235881225.98295346,
					"packets":	460700,
					"omitted":	false,
					"sender":	true
				}],
			"sum":	{
				"start":	42.000019,
				"end":	43.000007,
				"seconds":	0.9999880194664,
				"bytes":	29484800,
				"bits_per_second":	235881225.98295346,
				"packets":	460700,
				"omitted":	false,
				"sender":	true
			}
		}, {
			"streams":	[{
					"socket":	5,
					"start":	43.000007,
					"end":	44.000004,
					"seconds":	0.99999701976776123,
					"bytes":	28938880,
					"bits_per_second":	231511729.95872128,
					"packets":	452170,
					"omitted":	false,
					"sender":	true
				}],
			"sum":	{
				"start":	43.000007,
				"end":	44.000004,
				"seconds":	0.99999701976776123,
				"bytes":	28938880,
				"bits_per_second":	231511729.95872128,
				"packets":	452170,
				"omitted":	false,
				"sender":	true
			}
		}, {
			"streams":	[{
					"socket":	5,
					"start":	44.000004,
					"end":	45.000029,
					"seconds":	1.0000250339508057,
					"bytes":	28543360,
					"bits_per_second":	228341163.71854055,
					"packets":	445990,
					"omitted":	false,
					"sender":	true
				}],
			"sum":	{
				"start":	44.000004,
				"end":	45.000029,
				"seconds":	1.0000250339508057,
				"bytes":	28543360,
				"bits_per_second":	228341163.71854055,
				"packets":	445990,
				"omitted":	false,
				"sender":	true
			}
		}, {
			"streams":	[{
					"socket":	5,
					"start":	45.000029,
					"end":	46.000023,
					"seconds":	0.99999397993087769,
					"bytes":	29226880,
					"bits_per_second":	233816447.59117642,
					"packets":	456670,
					"omitted":	false,
					"sender":	true
				}],
			"sum":	{
				"start":	45.000029,
				"end":	46.000023,
				"seconds":	0.99999397993087769,
				"bytes":	29226880,
				"bits_per_second":	233816447.59117642,
				"packets":	456670,
				"omitted":	false,
				"sender":	true
			}
		}, {
			"streams":	[{
					"socket":	5,
					"start":	46.000023,
					"end":	47.000013,
					"seconds":	0.99998998641967773,
					"bytes":	28508800,
					"bits_per_second":	228072683.82413879,
					"packets":	445450,
					"omitted":	false,
					"sender":	true
				}],
			"sum":	{
				"start":	46.000023,
				"end":	47.000013,
				"seconds":	0.99998998641967773,
				"bytes":	28508800,
				"bits_per_second":	228072683.82413879,
				"packets":	445450,
				"omitted":	false,
				"sender":	true
			}
		}, {
			"streams":	[{
					"socket":	5,
					"start":	47.000013,
					"end":	48.000016,
					"seconds":	1.0000029802322388,
					"bytes":	29363840,
					"bits_per_second":	234910019.91358545,
					"packets":	458810,
					"omitted":	false,
					"sender":	true
				}],
			"sum":	{
				"start":	47.000013,
				"end":	48.000016,
				"seconds":	1.0000029802322388,
				"bytes":	29363840,
				"bits_per_second":	234910019.91358545,
				"packets":	458810,
				"omitted":	false,
				"sender":	true
			}
		}, {
			"streams":	[{
					"socket":	5,
					"start":	48.000016,
					"end":	49.000008,
					"seconds":	0.9999920129776,
					"bytes":	29477760,
					"bits_per_second":	235823963.53127915,
					"packets":	460590,
					"omitted":	false,
					"sender":	true
				}],
			"sum":	{
				"start":	48.000016,
				"end":	49.000008,
				"seconds":	0.9999920129776,
				"bytes":	29477760,
				"bits_per_second":	235823963.53127915,
				"packets":	460590,
				"omitted":	false,
				"sender":	true
			}
		}, {
			"streams":	[{
					"socket":	5,
					"start":	49.000008,
					"end":	50.000013,
					"seconds":	1.0000050067901611,
					"bytes":	29596800,
					"bits_per_second":	236773214.5261991,
					"packets":	462450,
					"omitted":	false,
					"sender":	true
				}],
			"sum":	{
				"start":	49.000008,
				"end":	50.000013,
				"seconds":	1.0000050067901611,
				"bytes":	29596800,
				"bits_per_second":	236773214.5261991,
				"packets":	462450,
				"omitted":	false,
				"sender":	true
			}
		}, {
			"streams":	[{
					"socket":	5,
					"start":	50.000013,
					"end":	51.000017,
					"seconds":	1.0000040531158447,
					"bytes":	29640960,
					"bits_per_second":	237126718.89793843,
					"packets":	463140,
					"omitted":	false,
					"sender":	true
				}],
			"sum":	{
				"start":	50.000013,
				"end":	51.000017,
				"seconds":	1.0000040531158447,
				"bytes":	29640960,
				"bits_per_second":	237126718.89793843,
				"packets":	463140,
				"omitted":	false,
				"sender":	true
			}
		}, {
			"streams":	[{
					"socket":	5,
					"start":	51.000017,
					"end":	52.000022,
					"seconds":	1.0000050067901611,
					"bytes":	29217280,
					"bits_per_second":	233737069.727539,
					"packets":	456520,
					"omitted":	false,
					"sender":	true
				}],
			"sum":	{
				"start":	51.000017,
				"end":	52.000022,
				"seconds":	1.0000050067901611,
				"bytes":	29217280,
				"bits_per_second":	233737069.727539,
				"packets":	456520,
				"omitted":	false,
				"sender":	true
			}
		}, {
			"streams":	[{
					"socket":	5,
					"start":	52.000022,
					"end":	53.000014,
					"seconds":	0.9999920129776,
					"bytes":	28661120,
					"bits_per_second":	229290791.35068661,
					"packets":	447830,
					"omitted":	false,
					"sender":	true
				}],
			"sum":	{
				"start":	52.000022,
				"end":	53.000014,
				"seconds":	0.9999920129776,
				"bytes":	28661120,
				"bits_per_second":	229290791.35068661,
				"packets":	447830,
				"omitted":	false,
				"sender":	true
			}
		}, {
			"streams":	[{
					"socket":	5,
					"start":	53.000014,
					"end":	54.000013,
					"seconds":	0.99999898672103882,
					"bytes":	29299200,
					"bits_per_second":	234393837.50634417,
					"packets":	457800,
					"omitted":	false,
					"sender":	true
				}],
			"sum":	{
				"start":	53.000014,
				"end":	54.000013,
				"seconds":	0.99999898672103882,
				"bytes":	29299200,
				"bits_per_second":	234393837.50634417,
				"packets":	457800,
				"omitted":	false,
				"sender":	true
			}
		}, {
			"streams":	[{
					"socket":	5,
					"start":	54.000013,
					"end":	55.000012,
					"seconds":	0.99999898672103882,
					"bytes":	29564800,
					"bits_per_second":	236518639.65936148,
					"packets":	461950,
					"omitted":	false,
					"sender":	true
				}],
			"sum":	{
				"start":	54.000013,
				"end":	55.000012,
				"seconds":	0.99999898672103882,
				"bytes":	29564800,
				"bits_per_second":	236518639.65936148,
				"packets":	461950,
				"omitted":	false,
				"sender":	true
			}
		}, {
			"streams":	[{
					"socket":	5,
					"start":	55.000012,
					"end":	56.000007,
					"seconds":	0.999994993209839,
					"bytes":	29480960,
					"bits_per_second":	235848860.845756,
					"packets":	460640,
					"omitted":	false,
					"sender":	true
				}],
			"sum":	{
				"start":	55.000012,
				"end":	56.000007,
				"seconds":	0.999994993209839,
				"bytes":	29480960,
				"bits_per_second":	235848860.845756,
				"packets":	460640,
				"omitted":	false,
				"sender":	true
			}
		}, {
			"streams":	[{
					"socket":	5,
					"start":	56.000007,
					"end":	57.00003,
					"seconds":	1.0000230073928833,
					"bytes":	29587200,
					"bits_per_second":	236692154.33061293,
					"packets":	462300,
					"omitted":	false,
					"sender":	true
				}],
			"sum":	{
				"start":	56.000007,
				"end":	57.00003,
				"seconds":	1.0000230073928833,
				"bytes":	29587200,
				"bits_per_second":	236692154.33061293,
				"packets":	462300,
				"omitted":	false,
				"sender":	true
			}
		}, {
			"streams":	[{
					"socket":	5,
					"start":	57.00003,
					"end":	58.000016,
					"seconds":	0.99998599290847778,
					"bytes":	29819520,
					"bits_per_second":	238559501.52477136,
					"packets":	465930,
					"omitted":	false,
					"sender":	true
				}],
			"sum":	{
				"start":	57.00003,
				"end":	58.000016,
				"seconds":	0.99998599290847778,
				"bytes":	29819520,
				"bits_per_second":	238559501.52477136,
				"packets":	465930,
				"omitted":	false,
				"sender":	true
			}
		}, {
			"streams":	[{
					"socket":	5,
					"start":	58.000016,
					"end":	59.000011,
					"seconds":	0.999994993209839,
					"bytes":	29495040,
					"bits_per_second":	235961501.40972367,
					"packets":	460860,
					"omitted":	false,
					"sender":	true
				}],
			"sum":	{
				"start":	58.000016,
				"end":	59.000011,
				"seconds":	0.999994993209839,
				"bytes":	29495040,
				"bits_per_second":	235961501.40972367,
				"packets":	460860,
				"omitted":	false,
				"sender":	true
			}
		}, {
			"streams":	[{
					"socket":	5,
					"start":	59.000011,
					"end":	60.000017,
					"seconds":	1.0000059604644775,
					"bytes":	30288640,
					"bits_per_second":	242307675.73370615,
					"packets":	473260,
					"omitted":	false,
					"sender":	true
				}],
			"sum":	{
				"start":	59.000011,
				"end":	60.000017,
				"seconds":	1.0000059604644775,
				"bytes":	30288640,
				"bits_per_second":	242307675.73370615,
				"packets":	473260,
				"omitted":	false,
				"sender":	true
			}
		}],
	"end":	{
		"streams":	[{
				"udp":	{
					"socket":	5,
					"start":	0,
					"end":	60.000017,
					"seconds":	60.000017,
					"bytes":	1695310080,
					"bits_per_second":	226041279.95497069,
					"jitter_ms":	0.00040577767344897726,
					"lost_packets":	3839505,
					"packets":	26489220,
					"lost_percent":	14.494594404818262,
					"out_of_order":	0,
					"sender":	true
				}
			}],
		"sum":	{
			"start":	0,
			"end":	60.00166,
			"seconds":	60.00166,
			"bytes":	1695310080,
			"bits_per_second":	226041279.95497069,
			"jitter_ms":	0.00040577767344897726,
			"lost_packets":	3839505,
			"packets":	26489220,
			"lost_percent":	14.494594404818262,
			"sender":	true
		},
		"sum_sent":	{
			"start":	0,
			"end":	60.000017,
			"seconds":	60.000017,
			"bytes":	1695310080,
			"bits_per_second":	226041279.95497069,
			"jitter_ms":	0,
			"lost_packets":	0,
			"packets":	26489220,
			"lost_percent":	0,
			"sender":	true
		},
		"sum_received":	{
			"start":	0,
			"end":	60.00166,
			"seconds":	60.00166,
			"bytes":	1449581760,
			"bits_per_second":	193272220.80189115,
			"jitter_ms":	0.00040577767344897726,
			"lost_packets":	3839505,
			"packets":	26489220,
			"lost_percent":	14.494594404818262,
			"sender":	false
		},
		"cpu_utilization_percent":	{
			"host_total":	99.970344928281946,
			"host_user":	21.924010853616256,
			"host_system":	78.046332408088645,
			"remote_total":	98.823622801317555,
			"remote_user":	34.234258768084686,
			"remote_system":	64.5893640332329
		}
	}
}
